env_fields/__init__.py
env_fields-0.2.0.dist-info/LICENSE
env_fields-0.2.0.dist-info/METADATA
env_fields-0.2.0.dist-info/WHEEL
env_fields-0.2.0.dist-info/entry_points.txt
env_fields-0.2.0.dist-info/top_level.txt
env_fields-0.2.0.dist-info/RECORD
